colab_env_switcher/__init__.py
colab_env_switcher/switcher.py
colab_env_switcher-0.1.2.post1.dist-info/licenses/LICENSE
colab_env_switcher-0.1.2.post1.dist-info/METADATA
colab_env_switcher-0.1.2.post1.dist-info/WHEEL
colab_env_switcher-0.1.2.post1.dist-info/top_level.txt
colab_env_switcher-0.1.2.post1.dist-info/RECORD
