Metadata-Version: 2.4
Name: colab-env-switcher
Version: 0.1.2.post1
Summary: A Python environment switcher for Google Colab
Home-page: https://github.com/911218sky/colab-env-switcher
Author: 911218sky
Author-email: 911218sky <sky@sky1218.com>
License: MIT
Project-URL: Homepage, https://github.com/911218sky/colab-env-switcher
Project-URL: Repository, https://github.com/911218sky/colab-env-switcher
Classifier: Programming Language :: Python :: 3
Classifier: License :: OSI Approved :: MIT License
Classifier: Operating System :: OS Independent
Classifier: Intended Audience :: Developers
Classifier: Topic :: Software Development :: Libraries :: Python Modules
Requires-Python: >=3.7
License-File: LICENSE
Dynamic: author
Dynamic: home-page
Dynamic: license-file
Dynamic: requires-python
